meta_learning/__init__.py
meta_learning/_version.py
meta_learning/bench.py
meta_learning/cli.py
meta_learning/continual_meta_learning.py
meta_learning/data.py
meta_learning/eval.py
meta_learning/hardware_utils.py
meta_learning/leakage_guard.py
meta_learning/py.typed
meta_learning/toolkit.py
meta_learning/uncertainty_components.py
meta_learning/algorithms/__init__.py
meta_learning/algorithms/factory.py
meta_learning/algorithms/maml_research_accurate.py
meta_learning/algorithms/strategies.py
meta_learning/algorithms/ttc_config.py
meta_learning/algorithms/ttc_scaler.py
meta_learning/algos/maml.py
meta_learning/algos/protonet.py
meta_learning/algos/ttcs.py
meta_learning/core/bn_policy.py
meta_learning/core/episode.py
meta_learning/core/math_utils.py
meta_learning/core/seed.py
meta_learning/evaluation/__init__.py
meta_learning/evaluation/few_shot_evaluation_harness.py
meta_learning/few_shot_modules/__init__.py
meta_learning/few_shot_modules/few_shot_learning.py
meta_learning/few_shot_modules/uncertainty_components.py
meta_learning/research_patches/__init__.py
meta_learning/research_patches/batch_norm_policy.py
meta_learning/research_patches/determinism_hooks.py
meta_learning_toolkit-2.5.0.dist-info/METADATA
meta_learning_toolkit-2.5.0.dist-info/WHEEL
meta_learning_toolkit-2.5.0.dist-info/entry_points.txt
meta_learning_toolkit-2.5.0.dist-info/licenses/LICENSE
meta_learning_toolkit-2.5.0.dist-info/RECORD
