Metadata-Version: 2.4
Name: meta-learning-toolkit
Version: 2.5.0
Summary: Production-ready meta-learning algorithms with research-accurate implementations of MAML, Prototypical Networks, and test-time compute scaling
Project-URL: Homepage, https://github.com/benedictchen/meta-learning
Project-URL: Documentation, https://github.com/benedictchen/meta-learning/blob/main/README.md
Project-URL: Repository, https://github.com/benedictchen/meta-learning
Project-URL: Issues, https://github.com/benedictchen/meta-learning/issues
Project-URL: Funding, https://www.paypal.com/cgi-bin/webscr?cmd=_s-xclick&hosted_button_id=WXQKYYKPHWXHS
Project-URL: Sponsor, https://github.com/sponsors/benedictchen
Author-email: Benedict Chen <benedict@benedictchen.com>
Maintainer-email: Benedict Chen <benedict@benedictchen.com>
License: Custom Non-Commercial License
License-File: LICENSE
Keywords: MAML,few-shot,meta-learning,prototypical-networks,test-time-compute
Classifier: Development Status :: 4 - Beta
Classifier: Intended Audience :: Science/Research
Classifier: License :: Other/Proprietary License
Classifier: Programming Language :: Python :: 3
Classifier: Programming Language :: Python :: 3.9
Classifier: Programming Language :: Python :: 3.10
Classifier: Programming Language :: Python :: 3.11
Classifier: Topic :: Scientific/Engineering :: Artificial Intelligence
Classifier: Topic :: Scientific/Engineering :: Information Analysis
Requires-Python: >=3.9
Requires-Dist: numpy>=1.21.0
Requires-Dist: pyyaml>=6.0
Requires-Dist: requests>=2.25.0
Requires-Dist: rich>=12.0.0
Requires-Dist: scikit-learn>=1.0.0
Requires-Dist: scipy>=1.7.0
Requires-Dist: torch>=2.0.0
Requires-Dist: torchvision>=0.15.0
Requires-Dist: tqdm>=4.64.0
Provides-Extra: all
Requires-Dist: build>=0.10.0; extra == 'all'
Requires-Dist: h5py>=3.7.0; extra == 'all'
Requires-Dist: higher>=0.2.1; extra == 'all'
Requires-Dist: learn2learn>=0.1.7; extra == 'all'
Requires-Dist: matplotlib>=3.5.0; extra == 'all'
Requires-Dist: mypy>=1.5.0; extra == 'all'
Requires-Dist: pillow>=9.0.0; extra == 'all'
Requires-Dist: pre-commit>=3.0.0; extra == 'all'
Requires-Dist: pytest-benchmark>=4.0; extra == 'all'
Requires-Dist: pytest-cov>=4.0; extra == 'all'
Requires-Dist: pytest-mock>=3.10; extra == 'all'
Requires-Dist: pytest>=7.0; extra == 'all'
Requires-Dist: ruff>=0.1.0; extra == 'all'
Requires-Dist: seaborn>=0.11.0; extra == 'all'
Requires-Dist: torchmeta>=1.8.0; extra == 'all'
Requires-Dist: torchvision>=0.15.0; extra == 'all'
Requires-Dist: twine>=4.0.0; extra == 'all'
Requires-Dist: wandb>=0.15.0; extra == 'all'
Provides-Extra: datasets
Requires-Dist: h5py>=3.7.0; extra == 'datasets'
Requires-Dist: pillow>=9.0.0; extra == 'datasets'
Requires-Dist: torchvision>=0.15.0; extra == 'datasets'
Provides-Extra: dev
Requires-Dist: build>=0.10.0; extra == 'dev'
Requires-Dist: mypy>=1.5.0; extra == 'dev'
Requires-Dist: pre-commit>=3.0.0; extra == 'dev'
Requires-Dist: ruff>=0.1.0; extra == 'dev'
Requires-Dist: twine>=4.0.0; extra == 'dev'
Provides-Extra: research
Requires-Dist: higher>=0.2.1; extra == 'research'
Requires-Dist: learn2learn>=0.1.7; extra == 'research'
Requires-Dist: torchmeta>=1.8.0; extra == 'research'
Provides-Extra: test
Requires-Dist: pytest-benchmark>=4.0; extra == 'test'
Requires-Dist: pytest-cov>=4.0; extra == 'test'
Requires-Dist: pytest-mock>=3.10; extra == 'test'
Requires-Dist: pytest>=7.0; extra == 'test'
Provides-Extra: visualization
Requires-Dist: matplotlib>=3.5.0; extra == 'visualization'
Requires-Dist: seaborn>=0.11.0; extra == 'visualization'
Requires-Dist: wandb>=0.15.0; extra == 'visualization'
